Workbook

Sheet Orders
A1: order_id | B1: customer_id | C1: order_status | D1: order_date | E1: required_date | F1: shipped_date | G1: store_id | H1: staff_id | I1: customer name | J1: customer state | K1: customer city | L1: staff name | M1: store name | N1: store city | O1: store state
A2: 1 | B2: 259 | C2: 4 | D2: 42370 | E2: 42372 | F2: 42372 | G2: 1 | H2: 2 | I2: =VLOOKUP(B2,Customers!A:J, 10,FALSE) -> Johnathan Velazquez | J2: =VLOOKUP(B2,Customers!A:J,8,FALSE) -> CA | K2: =VLOOKUP(B2,Customers!A:J,7,FALSE) -> Pleasanton | L2: =VLOOKUP(H2,Staff!A:I,9,FALSE) -> Mireya Copeland | M2: =VLOOKUP(G2,Store!A:H,2,FALSE) -> Santa Cruz Bikes | N2: =VLOOKUP(G2,Store!A:H,6,FALSE) -> Santa Cruz | O2: CA
A3: 2 | B3: 1212 | C3: 4 | D3: 42370 | E3: 42373 | F3: 42372 | G3: 2 | H3: 6 | I3: =VLOOKUP(B3,Customers!A:J, 10,FALSE) -> Jaqueline Cummings | J3: =VLOOKUP(B3,Customers!A:J,8,FALSE) -> NY | K3: =VLOOKUP(B3,Customers!A:J,7,FALSE) -> Huntington Station | L3: =VLOOKUP(H3,Staff!A:I,9,FALSE) -> Marcelene Boyer | M3: =VLOOKUP(G3,Store!A:H,2,FALSE) -> Baldwin Bikes | N3: =VLOOKUP(G3,Store!A:H,6,FALSE) -> Baldwin | O3: NY
A4: 3 | B4: 523 | C4: 4 | D4: 42371 | E4: 42374 | F4: 42372 | G4: 2 | H4: 7 | I4: =VLOOKUP(B4,Customers!A:J, 10,FALSE) -> Joshua Robertson | J4: =VLOOKUP(B4,Customers!A:J,8,FALSE) -> NY | K4: =VLOOKUP(B4,Customers!A:J,7,FALSE) -> Patchogue | L4: =VLOOKUP(H4,Staff!A:I,9,FALSE) -> Venita Daniel | M4: =VLOOKUP(G4,Store!A:H,2,FALSE) -> Baldwin Bikes | N4: =VLOOKUP(G4,Store!A:H,6,FALSE) -> Baldwin | O4: NY
A5: 4 | B5: 175 | C5: 4 | D5: 42372 | E5: 42373 | F5: 42374 | G5: 1 | H5: 3 | I5: =VLOOKUP(B5,Customers!A:J, 10,FALSE) -> Nova Hess | J5: =VLOOKUP(B5,Customers!A:J,8,FALSE) -> CA | K5: =VLOOKUP(B5,Customers!A:J,7,FALSE) -> Duarte | L5: =VLOOKUP(H5,Staff!A:I,9,FALSE) -> Genna Serrano | M5: =VLOOKUP(G5,Store!A:H,2,FALSE) -> Santa Cruz Bikes | N5: =VLOOKUP(G5,Store!A:H,6,FALSE) -> Santa Cruz | O5: CA
A6: 5 | B6: 1324 | C6: 4 | D6: 42372 | E6: 42375 | F6: 42375 | G6: 2 | H6: 6 | I6: =VLOOKUP(B6,Customers!A:J, 10,FALSE) -> Arla Ellis | J6: =VLOOKUP(B6,Customers!A:J,8,FALSE) -> NY | K6: =VLOOKUP(B6,Customers!A:J,7,FALSE) -> Utica | L6: =VLOOKUP(H6,Staff!A:I,9,FALSE) -> Marcelene Boyer | M6: =VLOOKUP(G6,Store!A:H,2,FALSE) -> Baldwin Bikes | N6: =VLOOKUP(G6,Store!A:H,6,FALSE) -> Baldwin | O6: NY
A7: 6 | B7: 94 | C7: 4 | D7: 42373 | E7: 42376 | F7: 42374 | G7: 2 | H7: 6 | I7: =VLOOKUP(B7,Customers!A:J, 10,FALSE) -> Sharyn Hopkins | J7: =VLOOKUP(B7,Customers!A:J,8,FALSE) -> NY | K7: =VLOOKUP(B7,Customers!A:J,7,FALSE) -> Baldwinsville | L7: =VLOOKUP(H7,Staff!A:I,9,FALSE) -> Marcelene Boyer | M7: =VLOOKUP(G7,Store!A:H,2,FALSE) -> Baldwin Bikes | N7: =VLOOKUP(G7,Store!A:H,6,FALSE) -> Baldwin | O7: NY
A8: 7 | B8: 324 | C8: 4 | D8: 42373 | E8: 42376 | F8: 42374 | G8: 2 | H8: 6 | I8: =VLOOKUP(B8,Customers!A:J, 10,FALSE) -> Laureen Paul | J8: =VLOOKUP(B8,Customers!A:J,8,FALSE) -> NY | K8: =VLOOKUP(B8,Customers!A:J,7,FALSE) -> Bellmore | L8: =VLOOKUP(H8,Staff!A:I,9,FALSE) -> Marcelene Boyer | M8: =VLOOKUP(G8,Store!A:H,2,FALSE) -> Baldwin Bikes | N8: =VLOOKUP(G8,Store!A:H,6,FALSE) -> Baldwin | O8: NY
A9: 8 | B9: 1204 | C9: 4 | D9: 42373 | E9: 42374 | F9: 42374 | G9: 2 | H9: 7 | I9: =VLOOKUP(B9,Customers!A:J, 10,FALSE) -> Leslie Higgins | J9: =VLOOKUP(B9,Customers!A:J,8,FALSE) -> NY | K9: =VLOOKUP(B9,Customers!A:J,7,FALSE) -> Saratoga Springs | L9: =VLOOKUP(H9,Staff!A:I,9,FALSE) -> Venita Daniel | M9: =VLOOKUP(G9,Store!A:H,2,FALSE) -> Baldwin Bikes | N9: =VLOOKUP(G9,Store!A:H,6,FALSE) -> Baldwin | O9: NY
A10: 9 | B10: 60 | C10: 4 | D10: 42374 | E10: 42377 | F10: 42377 | G10: 1 | H10: 2 | I10: =VLOOKUP(B10,Customers!A:J, 10,FALSE) -> Neil Mccall | J10: =VLOOKUP(B10,Customers!A:J,8,FALSE) -> CA | K10: =VLOOKUP(B10,Customers!A:J,7,FALSE) -> San Carlos | L10: =VLOOKUP(H10,Staff!A:I,9,FALSE) -> Mireya Copeland | M10: =VLOOKUP(G10,Store!A:H,2,FALSE) -> Santa Cruz Bikes | N10: =VLOOKUP(G10,Store!A:H,6,FALSE) -> Santa Cruz | O10: CA
A11: 10 | B11: 442 | C11: 4 | D11: 42374 | E11: 42375 | F11: 42375 | G11: 2 | H11: 6 | I11: =VLOOKUP(B11,Customers!A:J, 10,FALSE) -> Alane Munoz | J11: =VLOOKUP(B11,Customers!A:J,8,FALSE) -> NY | K11: =VLOOKUP(B11,Customers!A:J,7,FALSE) -> Yonkers | L11: =VLOOKUP(H11,Staff!A:I,9,FALSE) -> Marcelene Boyer | M11: =VLOOKUP(G11,Store!A:H,2,FALSE) -> Baldwin Bikes | N11: =VLOOKUP(G11,Store!A:H,6,FALSE) -> Baldwin | O11: NY
A12: 11 | B12: 1326 | C12: 4 | D12: 42374 | E12: 42377 | F12: 42376 | G12: 2 | H12: 7 | I12: =VLOOKUP(B12,Customers!A:J, 10,FALSE) -> Tarra Guerrero | J12: =VLOOKUP(B12,Customers!A:J,8,FALSE) -> NY | K12: =VLOOKUP(B12,Customers!A:J,7,FALSE) -> Auburn | L12: =VLOOKUP(H12,Staff!A:I,9,FALSE) -> Venita Daniel | M12: =VLOOKUP(G12,Store!A:H,2,FALSE) -> Baldwin Bikes | N12: =VLOOKUP(G12,Store!A:H,6,FALSE) -> Baldwin | O12: NY
A13: 12 | B13: 91 | C13: 4 | D13: 42375 | E13: 42377 | F13: 42378 | G13: 1 | H13: 2 | I13: =VLOOKUP(B13,Customers!A:J, 10,FALSE) -> Marvin Mullins | J13: =VLOOKUP(B13,Customers!A:J,8,FALSE) -> CA | K13: =VLOOKUP(B13,Customers!A:J,7,FALSE) -> San Diego | L13: =VLOOKUP(H13,Staff!A:I,9,FALSE) -> Mireya Copeland | M13: =VLOOKUP(G13,Store!A:H,2,FALSE) -> Santa Cruz Bikes | N13: =VLOOKUP(G13,Store!A:H,6,FALSE) -> Santa Cruz | O13: CA
... A70: 69 | B70: 1413 | C70: 4 | D70: 42410 | E70: 42412 | F70: 42411 | G70: 2 | H70: 7 | I70: =VLOOKUP(B70,Customers!A:J, 10,FALSE) -> Ophelia Decker | J70: =VLOOKUP(B70,Customers!A:J,8,FALSE) -> NY | K70: =VLOOKUP(B70,Customers!A:J,7,FALSE) -> New Windsor | L70: =VLOOKUP(H70,Staff!A:I,9,FALSE) -> Venita Daniel | M70: =VLOOKUP(G70,Store!A:H,2,FALSE) -> Baldwin Bikes | N70: =VLOOKUP(G70,Store!A:H,6,FALSE) -> Baldwin | O70: NY
A71: 70 | B71: 50 | C71: 3 | D71: 42411 | E71: 42411 | F71: NULL | G71: 3 | H71: 9 | I71: =VLOOKUP(B71,Customers!A:J, 10,FALSE) -> Cleotilde Booth | J71: =VLOOKUP(B71,Customers!A:J,8,FALSE) -> TX | K71: =VLOOKUP(B71,Customers!A:J,7,FALSE) -> Sugar Land | L71: =VLOOKUP(H71,Staff!A:I,9,FALSE) -> Layla Terrell | M71: =VLOOKUP(G71,Store!A:H,2,FALSE) -> Rowlett Bikes | N71: =VLOOKUP(G71,Store!A:H,6,FALSE) -> Rowlett | O71: TX
A72: 71 | B72: 797 | C72: 4 | D72: 42411 | E72: 42414 | F72: 42412 | G72: 2 | H72: 7 | I72: =VLOOKUP(B72,Customers!A:J, 10,FALSE) -> Cathey Lamb | J72: =VLOOKUP(B72,Customers!A:J,8,FALSE) -> NY | K72: =VLOOKUP(B72,Customers!A:J,7,FALSE) -> Bayside | L72: =VLOOKUP(H72,Staff!A:I,9,FALSE) -> Venita Daniel | M72: =VLOOKUP(G72,Store!A:H,2,FALSE) -> Baldwin Bikes | N72: =VLOOKUP(G72,Store!A:H,6,FALSE) -> Baldwin | O72: NY
A73: 72 | B73: 1386 | C73: 4 | D73: 42412 | E73: 42415 | F73: 42413 | G73: 1 | H73: 2 | I73: =VLOOKUP(B73,Customers!A:J, 10,FALSE) -> Cesar Wilkins | J73: =VLOOKUP(B73,Customers!A:J,8,FALSE) -> CA | K73: =VLOOKUP(B73,Customers!A:J,7,FALSE) -> San Diego | L73: =VLOOKUP(H73,Staff!A:I,9,FALSE) -> Mireya Copeland | M73: =VLOOKUP(G73,Store!A:H,2,FALSE) -> Santa Cruz Bikes | N73: =VLOOKUP(G73,Store!A:H,6,FALSE) -> Santa Cruz | O73: CA
A74: 73 | B74: 612 | C74: 4 | D74: 42412 | E74: 42415 | F74: 42414 | G74: 2 | H74: 7 | I74: =VLOOKUP(B74,Customers!A:J, 10,FALSE) -> Gabriel Wagner | J74: =VLOOKUP(B74,Customers!A:J,8,FALSE) -> NY | K74: =VLOOKUP(B74,Customers!A:J,7,FALSE) -> Ballston Spa | L74: =VLOOKUP(H74,Staff!A:I,9,FALSE) -> Venita Daniel | M74: =VLOOKUP(G74,Store!A:H,2,FALSE) -> Baldwin Bikes | N74: =VLOOKUP(G74,Store!A:H,6,FALSE) -> Baldwin | O74: NY
A75: 74 | B75: 264 | C75: 4 | D75: 42413 | E75: 42415 | F75: 42415 | G75: 2 | H75: 7 | I75: =VLOOKUP(B75,Customers!A:J, 10,FALSE) -> Mariela Huffman | J75: =VLOOKUP(B75,Customers!A:J,8,FALSE) -> NY | K75: =VLOOKUP(B75,Customers!A:J,7,FALSE) -> Garden City | L75: =VLOOKUP(H75,Staff!A:I,9,FALSE) -> Venita Daniel | M75: =VLOOKUP(G75,Store!A:H,2,FALSE) -> Baldwin Bikes | N75: =VLOOKUP(G75,Store!A:H,6,FALSE) -> Baldwin | O75: NY
A76: 75 | B76: 587 | C76: 4 | D76: 42414 | E76: 42415 | F76: 42417 | G76: 2 | H76: 6 | I76: =VLOOKUP(B76,Customers!A:J, 10,FALSE) -> Euna Lopez | J76: =VLOOKUP(B76,Customers!A:J,8,FALSE) -> NY | K76: =VLOOKUP(B76,Customers!A:J,7,FALSE) -> Carmel | L76: =VLOOKUP(H76,Staff!A:I,9,FALSE) -> Marcelene Boyer | M76: =VLOOKUP(G76,Store!A:H,2,FALSE) -> Baldwin Bikes | N76: =VLOOKUP(G76,Store!A:H,6,FALSE) -> Baldwin | O76: NY
A77: 76 | B77: 9 | C77: 3 | D77: 42416 | E77: 42416 | F77: NULL | G77: 2 | H77: 6 | I77: =VLOOKUP(B77,Customers!A:J, 10,FALSE) -> Genoveva Baldwin | J77: =VLOOKUP(B77,Customers!A:J,8,FALSE) -> NY | K77: =VLOOKUP(B77,Customers!A:J,7,FALSE) -> Port Washington | L77: =VLOOKUP(H77,Staff!A:I,9,FALSE) -> Marcelene Boyer | M77: =VLOOKUP(G77,Store!A:H,2,FALSE) -> Baldwin Bikes | N77: =VLOOKUP(G77,Store!A:H,6,FALSE) -> Baldwin | O77: NY
A78: 77 | B78: 385 | C78: 4 | D78: 42416 | E78: 42419 | F78: 42419 | G78: 1 | H78: 2 | I78: =VLOOKUP(B78,Customers!A:J, 10,FALSE) -> Rochelle Ward | J78: =VLOOKUP(B78,Customers!A:J,8,FALSE) -> CA | K78: =VLOOKUP(B78,Customers!A:J,7,FALSE) -> Glendora | L78: =VLOOKUP(H78,Staff!A:I,9,FALSE) -> Mireya Copeland | M78: =VLOOKUP(G78,Store!A:H,2,FALSE) -> Santa Cruz Bikes | N78: =VLOOKUP(G78,Store!A:H,6,FALSE) -> Santa Cruz | O78: CA
A79: 78 | B79: 1182 | C79: 4 | D79: 42416 | E79: 42418 | F79: 42419 | G79: 2 | H79: 7 | I79: =VLOOKUP(B79,Customers!A:J, 10,FALSE) -> Trinidad Chapman | J79: =VLOOKUP(B79,Customers!A:J,8,FALSE) -> NY | K79: =VLOOKUP(B79,Customers!A:J,7,FALSE) -> Ronkonkoma | L79: =VLOOKUP(H79,Staff!A:I,9,FALSE) -> Venita Daniel | M79: =VLOOKUP(G79,Store!A:H,2,FALSE) -> Baldwin Bikes | N79: =VLOOKUP(G79,Store!A:H,6,FALSE) -> Baldwin | O79: NY
A80: 79 | B80: 529 | C80: 4 | D80: 42417 | E80: 42420 | F80: 42420 | G80: 1 | H80: 3 | I80: =VLOOKUP(B80,Customers!A:J, 10,FALSE) -> Ellena Clements | J80: =VLOOKUP(B80,Customers!A:J,8,FALSE) -> CA | K80: =VLOOKUP(B80,Customers!A:J,7,FALSE) -> Santa Monica | L80: =VLOOKUP(H80,Staff!A:I,9,FALSE) -> Genna Serrano | M80: =VLOOKUP(G80,Store!A:H,2,FALSE) -> Santa Cruz Bikes | N80: =VLOOKUP(G80,Store!A:H,6,FALSE) -> Santa Cruz | O80: CA
A81: 80 | B81: 397 | C81: 4 | D81: 42417 | E81: 42420 | F81: 42419 | G81: 2 | H81: 6 | I81: =VLOOKUP(B81,Customers!A:J, 10,FALSE) -> Jeannie Wilcox | J81: =VLOOKUP(B81,Customers!A:J,8,FALSE) -> NY | K81: =VLOOKUP(B81,Customers!A:J,7,FALSE) -> Franklin Square | L81: =VLOOKUP(H81,Staff!A:I,9,FALSE) -> Marcelene Boyer | M81: =VLOOKUP(G81,Store!A:H,2,FALSE) -> Baldwin Bikes | N81: =VLOOKUP(G81,Store!A:H,6,FALSE) -> Baldwin | O81: NY
A82: 81 | B82: 521 | C82: 4 | D82: 42417 | E82: 42419 | F82: 42418 | G82: 2 | H82: 6 | I82: =VLOOKUP(B82,Customers!A:J, 10,FALSE) -> Max Charles | J82: =VLOOKUP(B82,Customers!A:J,8,FALSE) -> NY | K82: =VLOOKUP(B82,Customers!A:J,7,FALSE) -> Glen Cove | L82: =VLOOKUP(H82,Staff!A:I,9,FALSE) -> Marcelene Boyer | M82: =VLOOKUP(G82,Store!A:H,2,FALSE) -> Baldwin Bikes | N82: =VLOOKUP(G82,Store!A:H,6,FALSE) -> Baldwin | O82: NY
A83: 82 | B83: 1223 | C83: 4 | D83: 42418 | E83: 42421 | F83: 42420 | G83: 2 | H83: 6 | I83: =VLOOKUP(B83,Customers!A:J, 10,FALSE) -> Bronwyn Vargas | J83: =VLOOKUP(B83,Customers!A:J,8,FALSE) -> NY | K83: =VLOOKUP(B83,Customers!A:J,7,FALSE) -> New Windsor | L83: =VLOOKUP(H83,Staff!A:I,9,FALSE) -> Marcelene Boyer | M83: =VLOOKUP(G83,Store!A:H,2,FALSE) -> Baldwin Bikes | N83: =VLOOKUP(G83,Store!A:H,6,FALSE) -> Baldwin | O83: NY
A84: 83 | B84: 393 | C84: 4 | D84: 42419 | E84: 42420 | F84: 42420 | G84: 1 | H84: 3 | I84: =VLOOKUP(B84,Customers!A:J, 10,FALSE) -> Gertrude Terry | J84: =VLOOKUP(B84,Customers!A:J,8,FALSE) -> CA | K84: =VLOOKUP(B84,Customers!A:J,7,FALSE) -> Upland | L84: =VLOOKUP(H84,Staff!A:I,9,FALSE) -> Genna Serrano | M84: =VLOOKUP(G84,Store!A:H,2,FALSE) -> Santa Cruz Bikes | N84: =VLOOKUP(G84,Store!A:H,6,FALSE) -> Santa Cruz | O84: CA
A85: 84 | B85: 317 | C85: 4 | D85: 42420 | E85: 42422 | F85: 42421 | G85: 2 | H85: 7 | I85: =VLOOKUP(B85,Customers!A:J, 10,FALSE) -> Christia Wilkins | J85: =VLOOKUP(B85,Customers!A:J,8,FALSE) -> NY | K85: =VLOOKUP(B85,Customers!A:J,7,FALSE) -> Woodside | L85: =VLOOKUP(H85,Staff!A:I,9,FALSE) -> Venita Daniel | M85: =VLOOKUP(G85,Store!A:H,2,FALSE) -> Baldwin Bikes | N85: =VLOOKUP(G85,Store!A:H,6,FALSE) -> Baldwin | O85: NY
A86: 85 | B86: 1174 | C86: 4 | D86: 42420 | E86: 42423 | F86: 42421 | G86: 2 | H86: 7 | I86: =VLOOKUP(B86,Customers!A:J, 10,FALSE) -> Aaron Knapp | J86: =VLOOKUP(B86,Customers!A:J,8,FALSE) -> NY | K86: =VLOOKUP(B86,Customers!A:J,7,FALSE) -> Yonkers | L86: =VLOOKUP(H86,Staff!A:I,9,FALSE) -> Venita Daniel | M86: =VLOOKUP(G86,Store!A:H,2,FALSE) -> Baldwin Bikes | N86: =VLOOKUP(G86,Store!A:H,6,FALSE) -> Baldwin | O86: NY
A87: 86 | B87: 276 | C87: 4 | D87: 42421 | E87: 42422 | F87: 42423 | G87: 2 | H87: 7 | I87: =VLOOKUP(B87,Customers!A:J, 10,FALSE) -> Lavette Wright | J87: =VLOOKUP(B87,Customers!A:J,8,FALSE) -> NY | K87: =VLOOKUP(B87,Customers!A:J,7,FALSE) -> Ronkonkoma | L87: =VLOOKUP(H87,Staff!A:I,9,FALSE) -> Venita Daniel | M87: =VLOOKUP(G87,Store!A:H,2,FALSE) -> Baldwin Bikes | N87: =VLOOKUP(G87,Store!A:H,6,FALSE) -> Baldwin | O87: NY
A88: 87 | B88: 516 | C88: 4 | D88: 42421 | E88: 42422 | F88: 42423 | G88: 2 | H88: 6 | I88: =VLOOKUP(B88,Customers!A:J, 10,FALSE) -> Rosa Kinney | J88: =VLOOKUP(B88,Customers!A:J,8,FALSE) -> NY | K88: =VLOOKUP(B88,Customers!A:J,7,FALSE) -> Brooklyn | L88: =VLOOKUP(H88,Staff!A:I,9,FALSE) -> Marcelene Boyer | M88: =VLOOKUP(G88,Store!A:H,2,FALSE) -> Baldwin Bikes | N88: =VLOOKUP(G88,Store!A:H,6,FALSE) -> Baldwin | O88: NY
A89: 88 | B89: 1069 | C89: 4 | D89: 42421 | E89: 42422 | F89: 42423 | G89: 2 | H89: 6 | I89: =VLOOKUP(B89,Customers!A:J, 10,FALSE) -> Rodolfo Buck | J89: =VLOOKUP(B89,Customers!A:J,8,FALSE) -> NY | K89: =VLOOKUP(B89,Customers!A:J,7,FALSE) -> Shirley | L89: =VLOOKUP(H89,Staff!A:I,9,FALSE) -> Marcelene Boyer | M89: =VLOOKUP(G89,Store!A:H,2,FALSE) -> Baldwin Bikes | N89: =VLOOKUP(G89,Store!A:H,6,FALSE) -> Baldwin | O89: NY
... A158: 157 | B158: 43 | C158: 4 | D158: 42463 | E158: 42466 | F158: 42466 | G158: 3 | H158: 8 | I158: =VLOOKUP(B158,Customers!A:J, 10,FALSE) -> Mozelle Carter | J158: =VLOOKUP(B158,Customers!A:J,8,FALSE) -> TX | K158: =VLOOKUP(B158,Customers!A:J,7,FALSE) -> Houston | L158: =VLOOKUP(H158,Staff!A:I,9,FALSE) -> Kali Vargas | M158: =VLOOKUP(G158,Store!A:H,2,FALSE) -> Rowlett Bikes | N158: =VLOOKUP(G158,Store!A:H,6,FALSE) -> Rowlett | O158: TX
A159: 158 | B159: 117 | C159: 3 | D159: 42464 | E159: 42464 | F159: NULL | G159: 3 | H159: 9 | I159: =VLOOKUP(B159,Customers!A:J, 10,FALSE) -> Dacia William | J159: =VLOOKUP(B159,Customers!A:J,8,FALSE) -> TX | K159: =VLOOKUP(B159,Customers!A:J,7,FALSE) -> Sugar Land | L159: =VLOOKUP(H159,Staff!A:I,9,FALSE) -> Layla Terrell | M159: =VLOOKUP(G159,Store!A:H,2,FALSE) -> Rowlett Bikes | N159: =VLOOKUP(G159,Store!A:H,6,FALSE) -> Rowlett | O159: TX
A160: 159 | B160: 32 | C160: 4 | D160: 42464 | E160: 42466 | F160: 42466 | G160: 1 | H160: 2 | I160: =VLOOKUP(B160,Customers!A:J, 10,FALSE) -> Araceli Golden | J160: =VLOOKUP(B160,Customers!A:J,8,FALSE) -> CA | K160: =VLOOKUP(B160,Customers!A:J,7,FALSE) -> Fullerton | L160: =VLOOKUP(H160,Staff!A:I,9,FALSE) -> Mireya Copeland | M160: =VLOOKUP(G160,Store!A:H,2,FALSE) -> Santa Cruz Bikes | N160: =VLOOKUP(G160,Store!A:H,6,FALSE) -> Santa Cruz | O160: CA
A161: 160 | B161: 205 | C161: 4 | D161: 42464 | E161: 42466 | F161: 42466 | G161: 2 | H161: 7 | I161: =VLOOKUP(B161,Customers!A:J, 10,FALSE) -> Harris Pittman | J161: =VLOOKUP(B161,Customers!A:J,8,FALSE) -> NY | K161: =VLOOKUP(B161,Customers!A:J,7,FALSE) -> Jamaica | L161: =VLOOKUP(H161,Staff!A:I,9,FALSE) -> Venita Daniel | M161: =VLOOKUP(G161,Store!A:H,2,FALSE) -> Baldwin Bikes | N161: =VLOOKUP(G161,Store!A:H,6,FALSE) -> Baldwin | O161: NY
A162: 161 | B162: 251 | C162: 4 | D162: 42464 | E162: 42467 | F162: 42465 | G162: 2 | H162: 7 | I162: =VLOOKUP(B162,Customers!A:J, 10,FALSE) -> Kasie Rodriquez | J162: =VLOOKUP(B162,Customers!A:J,8,FALSE) -> NY | K162: =VLOOKUP(B162,Customers!A:J,7,FALSE) -> Ballston Spa | L162: =VLOOKUP(H162,Staff!A:I,9,FALSE) -> Venita Daniel | M162: =VLOOKUP(G162,Store!A:H,2,FALSE) -> Baldwin Bikes | N162: =VLOOKUP(G162,Store!A:H,6,FALSE) -> Baldwin | O162: NY
A163: 162 | B163: 31 | C163: 4 | D163: 42466 | E163: 42468 | F163: 42467 | G163: 1 | H163: 3 | I163: =VLOOKUP(B163,Customers!A:J, 10,FALSE) -> Williemae Holloway | J163: =VLOOKUP(B163,Customers!A:J,8,FALSE) -> CA | K163: =VLOOKUP(B163,Customers!A:J,7,FALSE) -> Oakland | L163: =VLOOKUP(H163,Staff!A:I,9,FALSE) -> Genna Serrano | M163: =VLOOKUP(G163,Store!A:H,2,FALSE) -> Santa Cruz Bikes | N163: =VLOOKUP(G163,Store!A:H,6,FALSE) -> Santa Cruz | O163: CA
A164: 163 | B164: 1325 | C164: 4 | D164: 42466 | E164: 42467 | F164: 42467 | G164: 2 | H164: 7 | I164: =VLOOKUP(B164,Customers!A:J, 10,FALSE) -> Magdalena Sherman | J164: =VLOOKUP(B164,Customers!A:J,8,FALSE) -> NY | K164: =VLOOKUP(B164,Customers!A:J,7,FALSE) -> Oswego | L164: =VLOOKUP(H164,Staff!A:I,9,FALSE) -> Venita Daniel | M164: =VLOOKUP(G164,Store!A:H,2,FALSE) -> Baldwin Bikes | N164: =VLOOKUP(G164,Store!A:H,6,FALSE) -> Baldwin | O164: NY
A165: 164 | B165: 610 | C165: 4 | D165: 42467 | E165: 42468 | F165: 42469 | G165: 2 | H165: 7 | I165: =VLOOKUP(B165,Customers!A:J, 10,FALSE) -> Leonore Dorsey | J165: =VLOOKUP(B165,Customers!A:J,8,FALSE) -> NY | K165: =VLOOKUP(B165,Customers!A:J,7,FALSE) -> Jackson Heights | L165: =VLOOKUP(H165,Staff!A:I,9,FALSE) -> Venita Daniel | M165: =VLOOKUP(G165,Store!A:H,2,FALSE) -> Baldwin Bikes | N165: =VLOOKUP(G165,Store!A:H,6,FALSE) -> Baldwin | O165: NY
A166: 165 | B166: 574 | C166: 4 | D166: 42468 | E166: 42470 | F166: 42470 | G166: 1 | H166: 3 | I166: =VLOOKUP(B166,Customers!A:J, 10,FALSE) -> Adriene Rivera | J166: =VLOOKUP(B166,Customers!A:J,8,FALSE) -> CA | K166: =VLOOKUP(B166,Customers!A:J,7,FALSE) -> Encino | L166: =VLOOKUP(H166,Staff!A:I,9,FALSE) -> Genna Serrano | M166: =VLOOKUP(G166,Store!A:H,2,FALSE) -> Santa Cruz Bikes | N166: =VLOOKUP(G166,Store!A:H,6,FALSE) -> Santa Cruz | O166: CA
A167: 166 | B167: 338 | C167: 4 | D167: 42468 | E167: 42471 | F167: 42471 | G167: 2 | H167: 6 | I167: =VLOOKUP(B167,Customers!A:J, 10,FALSE) -> Abbey Pugh | J167: =VLOOKUP(B167,Customers!A:J,8,FALSE) -> NY | K167: =VLOOKUP(B167,Customers!A:J,7,FALSE) -> Forest Hills | L167: =VLOOKUP(H167,Staff!A:I,9,FALSE) -> Marcelene Boyer | M167: =VLOOKUP(G167,Store!A:H,2,FALSE) -> Baldwin Bikes | N167: =VLOOKUP(G167,Store!A:H,6,FALSE) -> Baldwin | O167: NY
A168: 167 | B168: 1034 | C168: 4 | D168: 42468 | E168: 42469 | F168: 42471 | G168: 2 | H168: 7 | I168: =VLOOKUP(B168,Customers!A:J, 10,FALSE) -> Rico Salas | J168: =VLOOKUP(B168,Customers!A:J,8,FALSE) -> NY | K168: =VLOOKUP(B168,Customers!A:J,7,FALSE) -> Centereach | L168: =VLOOKUP(H168,Staff!A:I,9,FALSE) -> Venita Daniel | M168: =VLOOKUP(G168,Store!A:H,2,FALSE) -> Baldwin Bikes | N168: =VLOOKUP(G168,Store!A:H,6,FALSE) -> Baldwin | O168: NY
A169: 168 | B169: 1147 | C169: 4 | D169: 42469 | E169: 42472 | F169: 42471 | G169: 1 | H169: 3 | I169: =VLOOKUP(B169,Customers!A:J, 10,FALSE) -> Kandace Ayers | J169: =VLOOKUP(B169,Customers!A:J,8,FALSE) -> CA | K169: =VLOOKUP(B169,Customers!A:J,7,FALSE) -> Santa Monica | L169: =VLOOKUP(H169,Staff!A:I,9,FALSE) -> Genna Serrano | M169: =VLOOKUP(G169,Store!A:H,2,FALSE) -> Santa Cruz Bikes | N169: =VLOOKUP(G169,Store!A:H,6,FALSE) -> Santa Cruz | O169: CA
A170: 169 | B170: 99 | C170: 4 | D170: 42470 | E170: 42471 | F170: 42471 | G170: 2 | H170: 7 | I170: =VLOOKUP(B170,Customers!A:J, 10,FALSE) -> Carie Kidd | J170: =VLOOKUP(B170,Customers!A:J,8,FALSE) -> NY | K170: =VLOOKUP(B170,Customers!A:J,7,FALSE) -> Monroe | L170: =VLOOKUP(H170,Staff!A:I,9,FALSE) -> Venita Daniel | M170: =VLOOKUP(G170,Store!A:H,2,FALSE) -> Baldwin Bikes | N170: =VLOOKUP(G170,Store!A:H,6,FALSE) -> Baldwin | O170: NY
A171: 170 | B171: 1200 | C171: 4 | D171: 42470 | E171: 42471 | F171: 42473 | G171: 2 | H171: 7 | I171: =VLOOKUP(B171,Customers!A:J, 10,FALSE) -> Aubrey Durham | J171: =VLOOKUP(B171,Customers!A:J,8,FALSE) -> NY | K171: =VLOOKUP(B171,Customers!A:J,7,FALSE) -> Port Washington | L171: =VLOOKUP(H171,Staff!A:I,9,FALSE) -> Venita Daniel | M171: =VLOOKUP(G171,Store!A:H,2,FALSE) -> Baldwin Bikes | N171: =VLOOKUP(G171,Store!A:H,6,FALSE) -> Baldwin | O171: NY
... A185: 184 | B185: 134 | C185: 4 | D185: 42479 | E185: 42481 | F185: 42482 | G185: 2 | H185: 7 | I185: =VLOOKUP(B185,Customers!A:J, 10,FALSE) -> Brianna Moss | J185: =VLOOKUP(B185,Customers!A:J,8,FALSE) -> NY | K185: =VLOOKUP(B185,Customers!A:J,7,FALSE) -> Hempstead | L185: =VLOOKUP(H185,Staff!A:I,9,FALSE) -> Venita Daniel | M185: =VLOOKUP(G185,Store!A:H,2,FALSE) -> Baldwin Bikes | N185: =VLOOKUP(G185,Store!A:H,6,FALSE) -> Baldwin | O185: NY
A186: 185 | B186: 24 | C186: 3 | D186: 42480 | E186: 42480 | F186: NULL | G186: 1 | H186: 2 | I186: =VLOOKUP(B186,Customers!A:J, 10,FALSE) -> Corene Wall | J186: =VLOOKUP(B186,Customers!A:J,8,FALSE) -> CA | K186: =VLOOKUP(B186,Customers!A:J,7,FALSE) -> Atwater | L186: =VLOOKUP(H186,Staff!A:I,9,FALSE) -> Mireya Copeland | M186: =VLOOKUP(G186,Store!A:H,2,FALSE) -> Santa Cruz Bikes | N186: =VLOOKUP(G186,Store!A:H,6,FALSE) -> Santa Cruz | O186: CA
A187: 186 | B187: 1127 | C187: 4 | D187: 42481 | E187: 42482 | F187: 42484 | G187: 2 | H187: 6 | I187: =VLOOKUP(B187,Customers!A:J, 10,FALSE) -> Waldo Hart | J187: =VLOOKUP(B187,Customers!A:J,8,FALSE) -> NY | K187: =VLOOKUP(B187,Customers!A:J,7,FALSE) -> Queensbury | L187: =VLOOKUP(H187,Staff!A:I,9,FALSE) -> Marcelene Boyer | M187: =VLOOKUP(G187,Store!A:H,2,FALSE) -> Baldwin Bikes | N187: =VLOOKUP(G187,Store!A:H,6,FALSE) -> Baldwin | O187: NY
A188: 187 | B188: 183 | C188: 4 | D188: 42482 | E188: 42483 | F188: 42484 | G188: 2 | H188: 6 | I188: =VLOOKUP(B188,Customers!A:J, 10,FALSE) -> Jeniffer Ratliff | J188: =VLOOKUP(B188,Customers!A:J,8,FALSE) -> NY | K188: =VLOOKUP(B188,Customers!A:J,7,FALSE) -> Floral Park | L188: =VLOOKUP(H188,Staff!A:I,9,FALSE) -> Marcelene Boyer | M188: =VLOOKUP(G188,Store!A:H,2,FALSE) -> Baldwin Bikes | N188: =VLOOKUP(G188,Store!A:H,6,FALSE) -> Baldwin | O188: NY
A189: 188 | B189: 390 | C189: 4 | D189: 42482 | E189: 42483 | F189: 42485 | G189: 2 | H189: 6 | I189: =VLOOKUP(B189,Customers!A:J, 10,FALSE) -> Lorrie Pollard | J189: =VLOOKUP(B189,Customers!A:J,8,FALSE) -> NY | K189: =VLOOKUP(B189,Customers!A:J,7,FALSE) -> Ronkonkoma | L189: =VLOOKUP(H189,Staff!A:I,9,FALSE) -> Marcelene Boyer | M189: =VLOOKUP(G189,Store!A:H,2,FALSE) -> Baldwin Bikes | N189: =VLOOKUP(G189,Store!A:H,6,FALSE) -> Baldwin | O189: NY
A190: 189 | B190: 1288 | C190: 4 | D190: 42483 | E190: 42484 | F190: 42486 | G190: 1 | H190: 2 | I190: =VLOOKUP(B190,Customers!A:J, 10,FALSE) -> Allie Conley | J190: =VLOOKUP(B190,Customers!A:J,8,FALSE) -> CA | K190: =VLOOKUP(B190,Customers!A:J,7,FALSE) -> Lawndale | L190: =VLOOKUP(H190,Staff!A:I,9,FALSE) -> Mireya Copeland | M190: =VLOOKUP(G190,Store!A:H,2,FALSE) -> Santa Cruz Bikes | N190: =VLOOKUP(G190,Store!A:H,6,FALSE) -> Santa Cruz | O190: CA
A191: 190 | B191: 98 | C191: 4 | D191: 42483 | E191: 42485 | F191: 42485 | G191: 2 | H191: 6 | I191: =VLOOKUP(B191,Customers!A:J, 10,FALSE) -> Violet Valenzuela | J191: =VLOOKUP(B191,Customers!A:J,8,FALSE) -> NY | K191: =VLOOKUP(B191,Customers!A:J,7,FALSE) -> Plattsburgh | L191: =VLOOKUP(H191,Staff!A:I,9,FALSE) -> Marcelene Boyer | M191: =VLOOKUP(G191,Store!A:H,2,FALSE) -> Baldwin Bikes | N191: =VLOOKUP(G191,Store!A:H,6,FALSE) -> Baldwin | O191: NY
A192: 191 | B192: 919 | C192: 4 | D192: 42487 | E192: 42488 | F192: 42488 | G192: 1 | H192: 2 | I192: =VLOOKUP(B192,Customers!A:J, 10,FALSE) -> Ruthanne Hoover | J192: =VLOOKUP(B192,Customers!A:J,8,FALSE) -> CA | K192: =VLOOKUP(B192,Customers!A:J,7,FALSE) -> Torrance | L192: =VLOOKUP(H192,Staff!A:I,9,FALSE) -> Mireya Copeland | M192: =VLOOKUP(G192,Store!A:H,2,FALSE) -> Santa Cruz Bikes | N192: =VLOOKUP(G192,Store!A:H,6,FALSE) -> Santa Cruz | O192: CA
A193: 192 | B193: 728 | C193: 4 | D193: 42487 | E193: 42488 | F193: 42489 | G193: 2 | H193: 7 | I193: =VLOOKUP(B193,Customers!A:J, 10,FALSE) -> Viva Dawson | J193: =VLOOKUP(B193,Customers!A:J,8,FALSE) -> NY | K193: =VLOOKUP(B193,Customers!A:J,7,FALSE) -> Orchard Park | L193: =VLOOKUP(H193,Staff!A:I,9,FALSE) -> Venita Daniel | M193: =VLOOKUP(G193,Store!A:H,2,FALSE) -> Baldwin Bikes | N193: =VLOOKUP(G193,Store!A:H,6,FALSE) -> Baldwin | O193: NY
A194: 193 | B194: 1366 | C194: 4 | D194: 42488 | E194: 42490 | F194: 42490 | G194: 1 | H194: 3 | I194: =VLOOKUP(B194,Customers!A:J, 10,FALSE) -> Trena Rogers | J194: =VLOOKUP(B194,Customers!A:J,8,FALSE) -> CA | K194: =VLOOKUP(B194,Customers!A:J,7,FALSE) -> Campbell | L194: =VLOOKUP(H194,Staff!A:I,9,FALSE) -> Genna Serrano | M194: =VLOOKUP(G194,Store!A:H,2,FALSE) -> Santa Cruz Bikes | N194: =VLOOKUP(G194,Store!A:H,6,FALSE) -> Santa Cruz | O194: CA
A195: 194 | B195: 558 | C195: 4 | D195: 42488 | E195: 42490 | F195: 42491 | G195: 2 | H195: 7 | I195: =VLOOKUP(B195,Customers!A:J, 10,FALSE) -> Carroll Kelly | J195: =VLOOKUP(B195,Customers!A:J,8,FALSE) -> NY | K195: =VLOOKUP(B195,Customers!A:J,7,FALSE) -> Monroe | L195: =VLOOKUP(H195,Staff!A:I,9,FALSE) -> Venita Daniel | M195: =VLOOKUP(G195,Store!A:H,2,FALSE) -> Baldwin Bikes | N195: =VLOOKUP(G195,Store!A:H,6,FALSE) -> Baldwin | O195: NY
A196: 195 | B196: 727 | C196: 4 | D196: 42488 | E196: 42491 | F196: 42491 | G196: 2 | H196: 7 | I196: =VLOOKUP(B196,Customers!A:J, 10,FALSE) -> Kasha Sullivan | J196: =VLOOKUP(B196,Customers!A:J,8,FALSE) -> NY | K196: =VLOOKUP(B196,Customers!A:J,7,FALSE) -> Scarsdale | L196: =VLOOKUP(H196,Staff!A:I,9,FALSE) -> Venita Daniel | M196: =VLOOKUP(G196,Store!A:H,2,FALSE) -> Baldwin Bikes | N196: =VLOOKUP(G196,Store!A:H,6,FALSE) -> Baldwin | O196: NY
A197: 196 | B197: 1247 | C197: 4 | D197: 42488 | E197: 42490 | F197: 42491 | G197: 2 | H197: 6 | I197: =VLOOKUP(B197,Customers!A:J, 10,FALSE) -> Tammie Cherry | J197: =VLOOKUP(B197,Customers!A:J,8,FALSE) -> NY | K197: =VLOOKUP(B197,Customers!A:J,7,FALSE) -> Massapequa | L197: =VLOOKUP(H197,Staff!A:I,9,FALSE) -> Marcelene Boyer | M197: =VLOOKUP(G197,Store!A:H,2,FALSE) -> Baldwin Bikes | N197: =VLOOKUP(G197,Store!A:H,6,FALSE) -> Baldwin | O197: NY
A198: 197 | B198: 127 | C198: 4 | D198: 42490 | E198: 42493 | F198: 42493 | G198: 2 | H198: 7 | I198: =VLOOKUP(B198,Customers!A:J, 10,FALSE) -> Erlinda Nielsen | J198: =VLOOKUP(B198,Customers!A:J,8,FALSE) -> NY | K198: =VLOOKUP(B198,Customers!A:J,7,FALSE) -> Maspeth | L198: =VLOOKUP(H198,Staff!A:I,9,FALSE) -> Venita Daniel | M198: =VLOOKUP(G198,Store!A:H,2,FALSE) -> Baldwin Bikes | N198: =VLOOKUP(G198,Store!A:H,6,FALSE) -> Baldwin | O198: NY
... A239: 238 | B239: 1350 | C239: 4 | D239: 42516 | E239: 42519 | F239: 42519 | G239: 2 | H239: 6 | I239: =VLOOKUP(B239,Customers!A:J, 10,FALSE) -> Annett Rush | J239: =VLOOKUP(B239,Customers!A:J,8,FALSE) -> NY | K239: =VLOOKUP(B239,Customers!A:J,7,FALSE) -> Rosedale | L239: =VLOOKUP(H239,Staff!A:I,9,FALSE) -> Marcelene Boyer | M239: =VLOOKUP(G239,Store!A:H,2,FALSE) -> Baldwin Bikes | N239: =VLOOKUP(G239,Store!A:H,6,FALSE) -> Baldwin | O239: NY
A240: 239 | B240: 13 | C240: 3 | D240: 42517 | E240: 42517 | F240: NULL | G240: 3 | H240: 9 | I240: =VLOOKUP(B240,Customers!A:J, 10,FALSE) -> Lashawn Ortiz | J240: =VLOOKUP(B240,Customers!A:J,8,FALSE) -> TX | K240: =VLOOKUP(B240,Customers!A:J,7,FALSE) -> Longview | L240: =VLOOKUP(H240,Staff!A:I,9,FALSE) -> Layla Terrell | M240: =VLOOKUP(G240,Store!A:H,2,FALSE) -> Rowlett Bikes | N240: =VLOOKUP(G240,Store!A:H,6,FALSE) -> Rowlett | O240: TX
A241: 240 | B241: 65 | C241: 4 | D241: 42517 | E241: 42519 | F241: 42520 | G241: 2 | H241: 6 | I241: =VLOOKUP(B241,Customers!A:J, 10,FALSE) -> Kanesha Vega | J241: =VLOOKUP(B241,Customers!A:J,8,FALSE) -> NY | K241: =VLOOKUP(B241,Customers!A:J,7,FALSE) -> Rome | L241: =VLOOKUP(H241,Staff!A:I,9,FALSE) -> Marcelene Boyer | M241: =VLOOKUP(G241,Store!A:H,2,FALSE) -> Baldwin Bikes | N241: =VLOOKUP(G241,Store!A:H,6,FALSE) -> Baldwin | O241: NY
A242: 241 | B242: 1082 | C242: 4 | D242: 42517 | E242: 42519 | F242: 42519 | G242: 2 | H242: 7 | I242: =VLOOKUP(B242,Customers!A:J, 10,FALSE) -> Divina Madden | J242: =VLOOKUP(B242,Customers!A:J,8,FALSE) -> NY | K242: =VLOOKUP(B242,Customers!A:J,7,FALSE) -> Long Beach | L242: =VLOOKUP(H242,Staff!A:I,9,FALSE) -> Venita Daniel | M242: =VLOOKUP(G242,Store!A:H,2,FALSE) -> Baldwin Bikes | N242: =VLOOKUP(G242,Store!A:H,6,FALSE) -> Baldwin | O242: NY
A243: 242 | B243: 1168 | C243: 4 | D243: 42517 | E243: 42520 | F243: 42520 | G243: 2 | H243: 7 | I243: =VLOOKUP(B243,Customers!A:J, 10,FALSE) -> Almeta Benjamin | J243: =VLOOKUP(B243,Customers!A:J,8,FALSE) -> NY | K243: =VLOOKUP(B243,Customers!A:J,7,FALSE) -> Sunnyside | L243: =VLOOKUP(H243,Staff!A:I,9,FALSE) -> Venita Daniel | M243: =VLOOKUP(G243,Store!A:H,2,FALSE) -> Baldwin Bikes | N243: =VLOOKUP(G243,Store!A:H,6,FALSE) -> Baldwin | O243: NY
A244: 243 | B244: 802 | C244: 4 | D244: 42517 | E244: 42520 | F244: 42518 | G244: 3 | H244: 8 | I244: =VLOOKUP(B244,Customers!A:J, 10,FALSE) -> Barrett Sanders | J244: =VLOOKUP(B244,Customers!A:J,8,FALSE) -> TX | K244: =VLOOKUP(B244,Customers!A:J,7,FALSE) -> Longview | L244: =VLOOKUP(H244,Staff!A:I,9,FALSE) -> Kali Vargas | M244: =VLOOKUP(G244,Store!A:H,2,FALSE) -> Rowlett Bikes | N244: =VLOOKUP(G244,Store!A:H,6,FALSE) -> Rowlett | O244: TX
A245: 244 | B245: 956 | C245: 4 | D245: 42518 | E245: 42519 | F245: 42519 | G245: 2 | H245: 6 | I245: =VLOOKUP(B245,Customers!A:J, 10,FALSE) -> Venus Hewitt | J245: =VLOOKUP(B245,Customers!A:J,8,FALSE) -> NY | K245: =VLOOKUP(B245,Customers!A:J,7,FALSE) -> Farmingdale | L245: =VLOOKUP(H245,Staff!A:I,9,FALSE) -> Marcelene Boyer | M245: =VLOOKUP(G245,Store!A:H,2,FALSE) -> Baldwin Bikes | N245: =VLOOKUP(G245,Store!A:H,6,FALSE) -> Baldwin | O245: NY
A246: 245 | B246: 223 | C246: 4 | D246: 42519 | E246: 42521 | F246: 42520 | G246: 2 | H246: 7 | I246: =VLOOKUP(B246,Customers!A:J, 10,FALSE) -> Scarlet Yates | J246: =VLOOKUP(B246,Customers!A:J,8,FALSE) -> NY | K246: =VLOOKUP(B246,Customers!A:J,7,FALSE) -> Patchogue | L246: =VLOOKUP(H246,Staff!A:I,9,FALSE) -> Venita Daniel | M246: =VLOOKUP(G246,Store!A:H,2,FALSE) -> Baldwin Bikes | N246: =VLOOKUP(G246,Store!A:H,6,FALSE) -> Baldwin | O246: NY
A247: 246 | B247: 17 | C247: 3 | D247: 42520 | E247: 42520 | F247: NULL | G247: 2 | H247: 6 | I247: =VLOOKUP(B247,Customers!A:J, 10,FALSE) -> Caren Stephens | J247: =VLOOKUP(B247,Customers!A:J,8,FALSE) -> NY | K247: =VLOOKUP(B247,Customers!A:J,7,FALSE) -> Scarsdale | L247: =VLOOKUP(H247,Staff!A:I,9,FALSE) -> Marcelene Boyer | M247: =VLOOKUP(G247,Store!A:H,2,FALSE) -> Baldwin Bikes | N247: =VLOOKUP(G247,Store!A:H,6,FALSE) -> Baldwin | O247: NY
A248: 247 | B248: 928 | C248: 4 | D248: 42520 | E248: 42522 | F248: 42522 | G248: 1 | H248: 3 | I248: =VLOOKUP(B248,Customers!A:J, 10,FALSE) -> Joann Barber | J248: =VLOOKUP(B248,Customers!A:J,8,FALSE) -> CA | K248: =VLOOKUP(B248,Customers!A:J,7,FALSE) -> Santa Monica | L248: =VLOOKUP(H248,Staff!A:I,9,FALSE) -> Genna Serrano | M248: =VLOOKUP(G248,Store!A:H,2,FALSE) -> Santa Cruz Bikes | N248: =VLOOKUP(G248,Store!A:H,6,FALSE) -> Santa Cruz | O248: CA
A249: 248 | B249: 1376 | C249: 4 | D249: 42520 | E249: 42522 | F249: 42521 | G249: 2 | H249: 7 | I249: =VLOOKUP(B249,Customers!A:J, 10,FALSE) -> Kimberley Reynolds | J249: =VLOOKUP(B249,Customers!A:J,8,FALSE) -> NY | K249: =VLOOKUP(B249,Customers!A:J,7,FALSE) -> Port Washington | L249: =VLOOKUP(H249,Staff!A:I,9,FALSE) -> Venita Daniel | M249: =VLOOKUP(G249,Store!A:H,2,FALSE) -> Baldwin Bikes | N249: =VLOOKUP(G249,Store!A:H,6,FALSE) -> Baldwin | O249: NY
A250: 249 | B250: 145 | C250: 4 | D250: 42522 | E250: 42525 | F250: 42525 | G250: 2 | H250: 6 | I250: =VLOOKUP(B250,Customers!A:J, 10,FALSE) -> Miquel Neal | J250: =VLOOKUP(B250,Customers!A:J,8,FALSE) -> NY | K250: =VLOOKUP(B250,Customers!A:J,7,FALSE) -> Staten Island | L250: =VLOOKUP(H250,Staff!A:I,9,FALSE) -> Marcelene Boyer | M250: =VLOOKUP(G250,Store!A:H,2,FALSE) -> Baldwin Bikes | N250: =VLOOKUP(G250,Store!A:H,6,FALSE) -> Baldwin | O250: NY
A251: 250 | B251: 150 | C251: 4 | D251: 42522 | E251: 42523 | F251: 42525 | G251: 2 | H251: 7 | I251: =VLOOKUP(B251,Customers!A:J, 10,FALSE) -> Weldon Michael | J251: =VLOOKUP(B251,Customers!A:J,8,FALSE) -> NY | K251: =VLOOKUP(B251,Customers!A:J,7,FALSE) -> Huntington | L251: =VLOOKUP(H251,Staff!A:I,9,FALSE) -> Venita Daniel | M251: =VLOOKUP(G251,Store!A:H,2,FALSE) -> Baldwin Bikes | N251: =VLOOKUP(G251,Store!A:H,6,FALSE) -> Baldwin | O251: NY
A252: 251 | B252: 851 | C252: 4 | D252: 42522 | E252: 42525 | F252: 42525 | G252: 2 | H252: 7 | I252: =VLOOKUP(B252,Customers!A:J, 10,FALSE) -> Arlena Buckner | J252: =VLOOKUP(B252,Customers!A:J,8,FALSE) -> NY | K252: =VLOOKUP(B252,Customers!A:J,7,FALSE) -> New Hyde Park | L252: =VLOOKUP(H252,Staff!A:I,9,FALSE) -> Venita Daniel | M252: =VLOOKUP(G252,Store!A:H,2,FALSE) -> Baldwin Bikes | N252: =VLOOKUP(G252,Store!A:H,6,FALSE) -> Baldwin | O252: NY
A253: 252 | B253: 66 | C253: 4 | D253: 42522 | E253: 42525 | F253: 42523 | G253: 3 | H253: 8 | I253: =VLOOKUP(B253,Customers!A:J, 10,FALSE) -> Lorrie Becker | J253: =VLOOKUP(B253,Customers!A:J,8,FALSE) -> TX | K253: =VLOOKUP(B253,Customers!A:J,7,FALSE) -> Garland | L253: =VLOOKUP(H253,Staff!A:I,9,FALSE) -> Kali Vargas | M253: =VLOOKUP(G253,Store!A:H,2,FALSE) -> Rowlett Bikes | N253: =VLOOKUP(G253,Store!A:H,6,FALSE) -> Rowlett | O253: TX
A254: 253 | B254: 1267 | C254: 4 | D254: 42523 | E254: 42526 | F254: 42526 | G254: 2 | H254: 6 | I254: =VLOOKUP(B254,Customers!A:J, 10,FALSE) -> Earline Gordon | J254: =VLOOKUP(B254,Customers!A:J,8,FALSE) -> NY | K254: =VLOOKUP(B254,Customers!A:J,7,FALSE) -> Ronkonkoma | L254: =VLOOKUP(H254,Staff!A:I,9,FALSE) -> Marcelene Boyer | M254: =VLOOKUP(G254,Store!A:H,2,FALSE) -> Baldwin Bikes | N254: =VLOOKUP(G254,Store!A:H,6,FALSE) -> Baldwin | O254: NY
A255: 254 | B255: 510 | C255: 4 | D255: 42524 | E255: 42527 | F255: 42526 | G255: 2 | H255: 7 | I255: =VLOOKUP(B255,Customers!A:J, 10,FALSE) -> Faustino Delacruz | J255: =VLOOKUP(B255,Customers!A:J,8,FALSE) -> NY | K255: =VLOOKUP(B255,Customers!A:J,7,FALSE) -> South Richmond Hill | L255: =VLOOKUP(H255,Staff!A:I,9,FALSE) -> Venita Daniel | M255: =VLOOKUP(G255,Store!A:H,2,FALSE) -> Baldwin Bikes | N255: =VLOOKUP(G255,Store!A:H,6,FALSE) -> Baldwin | O255: NY
A256: 255 | B256: 801 | C256: 4 | D256: 42524 | E256: 42527 | F256: 42526 | G256: 2 | H256: 7 | I256: =VLOOKUP(B256,Customers!A:J, 10,FALSE) -> Ophelia Rodgers | J256: =VLOOKUP(B256,Customers!A:J,8,FALSE) -> NY | K256: =VLOOKUP(B256,Customers!A:J,7,FALSE) -> Hopewell Junction | L256: =VLOOKUP(H256,Staff!A:I,9,FALSE) -> Venita Daniel | M256: =VLOOKUP(G256,Store!A:H,2,FALSE) -> Baldwin Bikes | N256: =VLOOKUP(G256,Store!A:H,6,FALSE) -> Baldwin | O256: NY
A257: 256 | B257: 26 | C257: 4 | D257: 42525 | E257: 42526 | F257: 42528 | G257: 2 | H257: 7 | I257: =VLOOKUP(B257,Customers!A:J, 10,FALSE) -> Theo Reese | J257: =VLOOKUP(B257,Customers!A:J,8,FALSE) -> NY | K257: =VLOOKUP(B257,Customers!A:J,7,FALSE) -> Long Beach | L257: =VLOOKUP(H257,Staff!A:I,9,FALSE) -> Venita Daniel | M257: =VLOOKUP(G257,Store!A:H,2,FALSE) -> Baldwin Bikes | N257: =VLOOKUP(G257,Store!A:H,6,FALSE) -> Baldwin | O257: NY
A258: 257 | B258: 1314 | C258: 4 | D258: 42526 | E258: 42527 | F258: 42529 | G258: 1 | H258: 3 | I258: =VLOOKUP(B258,Customers!A:J, 10,FALSE) -> Joeann Garrison | J258: =VLOOKUP(B258,Customers!A:J,8,FALSE) -> CA | K258: =VLOOKUP(B258,Customers!A:J,7,FALSE) -> Ontario | L258: =VLOOKUP(H258,Staff!A:I,9,FALSE) -> Genna Serrano | M258: =VLOOKUP(G258,Store!A:H,2,FALSE) -> Santa Cruz Bikes | N258: =VLOOKUP(G258,Store!A:H,6,FALSE) -> Santa Cruz | O258: CA
A259: 258 | B259: 107 | C259: 4 | D259: 42527 | E259: 42528 | F259: 42528 | G259: 2 | H259: 7 | I259: =VLOOKUP(B259,Customers!A:J, 10,FALSE) -> Cecil Hopper | J259: =VLOOKUP(B259,Customers!A:J,8,FALSE) -> NY | K259: =VLOOKUP(B259,Customers!A:J,7,FALSE) -> Central Islip | L259: =VLOOKUP(H259,Staff!A:I,9,FALSE) -> Venita Daniel | M259: =VLOOKUP(G259,Store!A:H,2,FALSE) -> Baldwin Bikes | N259: =VLOOKUP(G259,Store!A:H,6,FALSE) -> Baldwin | O259: NY
... A264: 263 | B264: 1322 | C264: 4 | D264: 42530 | E264: 42531 | F264: 42533 | G264: 2 | H264: 6 | I264: =VLOOKUP(B264,Customers!A:J, 10,FALSE) -> Ai Forbes | J264: =VLOOKUP(B264,Customers!A:J,8,FALSE) -> NY | K264: =VLOOKUP(B264,Customers!A:J,7,FALSE) -> Franklin Square | L264: =VLOOKUP(H264,Staff!A:I,9,FALSE) -> Marcelene Boyer | M264: =VLOOKUP(G264,Store!A:H,2,FALSE) -> Baldwin Bikes | N264: =VLOOKUP(G264,Store!A:H,6,FALSE) -> Baldwin | O264: NY
A265: 264 | B265: 5 | C265: 3 | D265: 42531 | E265: 42531 | F265: NULL | G265: 1 | H265: 3 | I265: =VLOOKUP(B265,Customers!A:J, 10,FALSE) -> Charolette Rice | J265: =VLOOKUP(B265,Customers!A:J,8,FALSE) -> CA | K265: =VLOOKUP(B265,Customers!A:J,7,FALSE) -> Sacramento | L265: =VLOOKUP(H265,Staff!A:I,9,FALSE) -> Genna Serrano | M265: =VLOOKUP(G265,Store!A:H,2,FALSE) -> Santa Cruz Bikes | N265: =VLOOKUP(G265,Store!A:H,6,FALSE) -> Santa Cruz | O265: CA
A266: 265 | B266: 682 | C266: 4 | D266: 42531 | E266: 42533 | F266: 42532 | G266: 2 | H266: 7 | I266: =VLOOKUP(B266,Customers!A:J, 10,FALSE) -> Arnita Thomas | J266: =VLOOKUP(B266,Customers!A:J,8,FALSE) -> NY | K266: =VLOOKUP(B266,Customers!A:J,7,FALSE) -> Orchard Park | L266: =VLOOKUP(H266,Staff!A:I,9,FALSE) -> Venita Daniel | M266: =VLOOKUP(G266,Store!A:H,2,FALSE) -> Baldwin Bikes | N266: =VLOOKUP(G266,Store!A:H,6,FALSE) -> Baldwin | O266: NY
A267: 266 | B267: 933 | C267: 4 | D267: 42531 | E267: 42534 | F267: 42534 | G267: 2 | H267: 7 | I267: =VLOOKUP(B267,Customers!A:J, 10,FALSE) -> Lurline Rivers | J267: =VLOOKUP(B267,Customers!A:J,8,FALSE) -> NY | K267: =VLOOKUP(B267,Customers!A:J,7,FALSE) -> Howard Beach | L267: =VLOOKUP(H267,Staff!A:I,9,FALSE) -> Venita Daniel | M267: =VLOOKUP(G267,Store!A:H,2,FALSE) -> Baldwin Bikes | N267: =VLOOKUP(G267,Store!A:H,6,FALSE) -> Baldwin | O267: NY
A268: 267 | B268: 282 | C268: 4 | D268: 42532 | E268: 42535 | F268: 42535 | G268: 1 | H268: 3 | I268: =VLOOKUP(B268,Customers!A:J, 10,FALSE) -> Randolph Chase | J268: =VLOOKUP(B268,Customers!A:J,8,FALSE) -> CA | K268: =VLOOKUP(B268,Customers!A:J,7,FALSE) -> San Lorenzo | L268: =VLOOKUP(H268,Staff!A:I,9,FALSE) -> Genna Serrano | M268: =VLOOKUP(G268,Store!A:H,2,FALSE) -> Santa Cruz Bikes | N268: =VLOOKUP(G268,Store!A:H,6,FALSE) -> Santa Cruz | O268: CA
A269: 268 | B269: 540 | C269: 4 | D269: 42532 | E269: 42535 | F269: 42533 | G269: 1 | H269: 3 | I269: =VLOOKUP(B269,Customers!A:J, 10,FALSE) -> Shery Randolph | J269: =VLOOKUP(B269,Customers!A:J,8,FALSE) -> CA | K269: =VLOOKUP(B269,Customers!A:J,7,FALSE) -> Ontario | L269: =VLOOKUP(H269,Staff!A:I,9,FALSE) -> Genna Serrano | M269: =VLOOKUP(G269,Store!A:H,2,FALSE) -> Santa Cruz Bikes | N269: =VLOOKUP(G269,Store!A:H,6,FALSE) -> Santa Cruz | O269: CA
A270: 269 | B270: 764 | C270: 4 | D270: 42533 | E270: 42534 | F270: 42536 | G270: 2 | H270: 6 | I270: =VLOOKUP(B270,Customers!A:J, 10,FALSE) -> Terrell Mathis | J270: =VLOOKUP(B270,Customers!A:J,8,FALSE) -> NY | K270: =VLOOKUP(B270,Customers!A:J,7,FALSE) -> Selden | L270: =VLOOKUP(H270,Staff!A:I,9,FALSE) -> Marcelene Boyer | M270: =VLOOKUP(G270,Store!A:H,2,FALSE) -> Baldwin Bikes | N270: =VLOOKUP(G270,Store!A:H,6,FALSE) -> Baldwin | O270: NY
A271: 270 | B271: 879 | C271: 4 | D271: 42533 | E271: 42536 | F271: 42534 | G271: 2 | H271: 7 | I271: =VLOOKUP(B271,Customers!A:J, 10,FALSE) -> Ethelyn Ray | J271: =VLOOKUP(B271,Customers!A:J,8,FALSE) -> NY | K271: =VLOOKUP(B271,Customers!A:J,7,FALSE) -> Garden City | L271: =VLOOKUP(H271,Staff!A:I,9,FALSE) -> Venita Daniel | M271: =VLOOKUP(G271,Store!A:H,2,FALSE) -> Baldwin Bikes | N271: =VLOOKUP(G271,Store!A:H,6,FALSE) -> Baldwin | O271: NY
A272: 271 | B272: 350 | C272: 4 | D272: 42534 | E272: 42537 | F272: 42535 | G272: 2 | H272: 7 | I272: =VLOOKUP(B272,Customers!A:J, 10,FALSE) -> Christoper Mccall | J272: =VLOOKUP(B272,Customers!A:J,8,FALSE) -> NY | K272: =VLOOKUP(B272,Customers!A:J,7,FALSE) -> Bay Shore | L272: =VLOOKUP(H272,Staff!A:I,9,FALSE) -> Venita Daniel | M272: =VLOOKUP(G272,Store!A:H,2,FALSE) -> Baldwin Bikes | N272: =VLOOKUP(G272,Store!A:H,6,FALSE) -> Baldwin | O272: NY
A273: 272 | B273: 497 | C273: 4 | D273: 42536 | E273: 42539 | F273: 42537 | G273: 2 | H273: 7 | I273: =VLOOKUP(B273,Customers!A:J, 10,FALSE) -> Ezra Fowler | J273: =VLOOKUP(B273,Customers!A:J,8,FALSE) -> NY | K273: =VLOOKUP(B273,Customers!A:J,7,FALSE) -> Nanuet | L273: =VLOOKUP(H273,Staff!A:I,9,FALSE) -> Venita Daniel | M273: =VLOOKUP(G273,Store!A:H,2,FALSE) -> Baldwin Bikes | N273: =VLOOKUP(G273,Store!A:H,6,FALSE) -> Baldwin | O273: NY
A274: 273 | B274: 1340 | C274: 4 | D274: 42537 | E274: 42540 | F274: 42538 | G274: 2 | H274: 7 | I274: =VLOOKUP(B274,Customers!A:J, 10,FALSE) -> Tona Velasquez | J274: =VLOOKUP(B274,Customers!A:J,8,FALSE) -> NY | K274: =VLOOKUP(B274,Customers!A:J,7,FALSE) -> Whitestone | L274: =VLOOKUP(H274,Staff!A:I,9,FALSE) -> Venita Daniel | M274: =VLOOKUP(G274,Store!A:H,2,FALSE) -> Baldwin Bikes | N274: =VLOOKUP(G274,Store!A:H,6,FALSE) -> Baldwin | O274: NY
A275: 274 | B275: 411 | C275: 4 | D275: 42538 | E275: 42541 | F275: 42539 | G275: 2 | H275: 7 | I275: =VLOOKUP(B275,Customers!A:J, 10,FALSE) -> Octavia Case | J275: =VLOOKUP(B275,Customers!A:J,8,FALSE) -> NY | K275: =VLOOKUP(B275,Customers!A:J,7,FALSE) -> New York | L275: =VLOOKUP(H275,Staff!A:I,9,FALSE) -> Venita Daniel | M275: =VLOOKUP(G275,Store!A:H,2,FALSE) -> Baldwin Bikes | N275: =VLOOKUP(G275,Store!A:H,6,FALSE) -> Baldwin | O275: NY
A276: 275 | B276: 1341 | C276: 4 | D276: 42538 | E276: 42540 | F276: 42539 | G276: 2 | H276: 7 | I276: =VLOOKUP(B276,Customers!A:J, 10,FALSE) -> Rozanne Reyes | J276: =VLOOKUP(B276,Customers!A:J,8,FALSE) -> NY | K276: =VLOOKUP(B276,Customers!A:J,7,FALSE) -> Garden City | L276: =VLOOKUP(H276,Staff!A:I,9,FALSE) -> Venita Daniel | M276: =VLOOKUP(G276,Store!A:H,2,FALSE) -> Baldwin Bikes | N276: =VLOOKUP(G276,Store!A:H,6,FALSE) -> Baldwin | O276: NY
A277: 276 | B277: 1227 | C277: 4 | D277: 42539 | E277: 42540 | F277: 42540 | G277: 2 | H277: 6 | I277: =VLOOKUP(B277,Customers!A:J, 10,FALSE) -> Magali Dixon | J277: =VLOOKUP(B277,Customers!A:J,8,FALSE) -> NY | K277: =VLOOKUP(B277,Customers!A:J,7,FALSE) -> Troy | L277: =VLOOKUP(H277,Staff!A:I,9,FALSE) -> Marcelene Boyer | M277: =VLOOKUP(G277,Store!A:H,2,FALSE) -> Baldwin Bikes | N277: =VLOOKUP(G277,Store!A:H,6,FALSE) -> Baldwin | O277: NY
... A349: 348 | B349: 907 | C349: 4 | D349: 42584 | E349: 42587 | F349: 42586 | G349: 3 | H349: 9 | I349: =VLOOKUP(B349,Customers!A:J, 10,FALSE) -> Daina Sampson | J349: =VLOOKUP(B349,Customers!A:J,8,FALSE) -> TX | K349: =VLOOKUP(B349,Customers!A:J,7,FALSE) -> Longview | L349: =VLOOKUP(H349,Staff!A:I,9,FALSE) -> Layla Terrell | M349: =VLOOKUP(G349,Store!A:H,2,FALSE) -> Rowlett Bikes | N349: =VLOOKUP(G349,Store!A:H,6,FALSE) -> Rowlett | O349: TX
A350: 349 | B350: 30 | C350: 3 | D350: 42585 | E350: 42585 | F350: NULL | G350: 1 | H350: 3 | I350: =VLOOKUP(B350,Customers!A:J, 10,FALSE) -> Jamaal Albert | J350: =VLOOKUP(B350,Customers!A:J,8,FALSE) -> CA | K350: =VLOOKUP(B350,Customers!A:J,7,FALSE) -> Torrance | L350: =VLOOKUP(H350,Staff!A:I,9,FALSE) -> Genna Serrano | M350: =VLOOKUP(G350,Store!A:H,2,FALSE) -> Santa Cruz Bikes | N350: =VLOOKUP(G350,Store!A:H,6,FALSE) -> Santa Cruz | O350: CA
A351: 350 | B351: 31 | C351: 3 | D351: 42585 | E351: 42585 | F351: NULL | G351: 1 | H351: 3 | I351: =VLOOKUP(B351,Customers!A:J, 10,FALSE) -> Williemae Holloway | J351: =VLOOKUP(B351,Customers!A:J,8,FALSE) -> CA | K351: =VLOOKUP(B351,Customers!A:J,7,FALSE) -> Oakland | L351: =VLOOKUP(H351,Staff!A:I,9,FALSE) -> Genna Serrano | M351: =VLOOKUP(G351,Store!A:H,2,FALSE) -> Santa Cruz Bikes | N351: =VLOOKUP(G351,Store!A:H,6,FALSE) -> Santa Cruz | O351: CA
A352: 351 | B352: 1307 | C352: 4 | D352: 42585 | E352: 42588 | F352: 42586 | G352: 1 | H352: 2 | I352: =VLOOKUP(B352,Customers!A:J, 10,FALSE) -> Cinda Rocha | J352: =VLOOKUP(B352,Customers!A:J,8,FALSE) -> CA | K352: =VLOOKUP(B352,Customers!A:J,7,FALSE) -> Los Banos | L352: =VLOOKUP(H352,Staff!A:I,9,FALSE) -> Mireya Copeland | M352: =VLOOKUP(G352,Store!A:H,2,FALSE) -> Santa Cruz Bikes | N352: =VLOOKUP(G352,Store!A:H,6,FALSE) -> Santa Cruz | O352: CA
...

Sheet Pivot Table
Q1: Total Order Id by Store Name / State | R1: store state
Q2: Store name | R2: CA | S2: NY | T2: TX
Q4: Baldwin Bikes | S4: 1093
Q5: Rowlett Bikes | T5: 174
Q6: Santa Cruz Bikes | R6: 348
Q7: Grand Total | R7: 348 | S7: 1093 | T7: 174

Sheet Pivot Chart

Sheet Customers
A1: customer_id | B1: first_name | C1: last_name | D1: phone | E1: email | F1: street | G1: city | H1: state | I1: zip_code | J1: customer name
A2: 1 | B2: Debra | C2: Burks | D2: NULL | E2: debra.burks@yahoo.com | F2: 9273 Thorne Ave. | G2: Orchard Park | H2: NY | I2: 14127 | J2: =CONCATENATE(B2," ",C2) -> Debra Burks
A3: 2 | B3: Kasha | C3: Todd | D3: NULL | E3: kasha.todd@yahoo.com | F3: 910 Vine Street | G3: Campbell | H3: CA | I3: 95008 | J3: =CONCATENATE(B3," ",C3) -> Kasha Todd
A4: 3 | B4: Tameka | C4: Fisher | D4: NULL | E4: tameka.fisher@aol.com | F4: 769C Honey Creek St. | G4: Redondo Beach | H4: CA | I4: 90278 | J4: =CONCATENATE(B4," ",C4) -> Tameka Fisher
A5: 4 | B5: Daryl | C5: Spence | D5: NULL | E5: daryl.spence@aol.com | F5: 988 Pearl Lane | G5: Uniondale | H5: NY | I5: 11553 | J5: =CONCATENATE(B5," ",C5) -> Daryl Spence
A6: 5 | B6: Charolette | C6: Rice | D6: (916) 381-6003 | E6: charolette.rice@msn.com | F6: 107 River Dr. | G6: Sacramento | H6: CA | I6: 95820 | J6: =CONCATENATE(B6," ",C6) -> Charolette Rice
A7: 6 | B7: Lyndsey | C7: Bean | D7: NULL | E7: lyndsey.bean@hotmail.com | F7: 769 West Road | G7: Fairport | H7: NY | I7: 14450 | J7: =CONCATENATE(B7," ",C7) -> Lyndsey Bean
A8: 7 | B8: Latasha | C8: Hays | D8: (716) 986-3359 | E8: latasha.hays@hotmail.com | F8: 7014 Manor Station Rd. | G8: Buffalo | H8: NY | I8: 14215 | J8: =CONCATENATE(B8," ",C8) -> Latasha Hays
A9: 8 | B9: Jacquline | C9: Duncan | D9: NULL | E9: jacquline.duncan@yahoo.com | F9: 15 Brown St. | G9: Jackson Heights | H9: NY | I9: 11372 | J9: =CONCATENATE(B9," ",C9) -> Jacquline Duncan
A10: 9 | B10: Genoveva | C10: Baldwin | D10: NULL | E10: genoveva.baldwin@msn.com | F10: 8550 Spruce Drive | G10: Port Washington | H10: NY | I10: 11050 | J10: =CONCATENATE(B10," ",C10) -> Genoveva Baldwin
A11: 10 | B11: Pamelia | C11: Newman | D11: NULL | E11: pamelia.newman@gmail.com | F11: 476 Chestnut Ave. | G11: Monroe | H11: NY | I11: 10950 | J11: =CONCATENATE(B11," ",C11) -> Pamelia Newman
A12: 11 | B12: Deshawn | C12: Mendoza | D12: NULL | E12: deshawn.mendoza@yahoo.com | F12: 8790 Cobblestone Street | G12: Monsey | H12: NY | I12: 10952 | J12: =CONCATENATE(B12," ",C12) -> Deshawn Mendoza
A13: 12 | B13: Robby | C13: Sykes | D13: (516) 583-7761 | E13: robby.sykes@hotmail.com | F13: 486 Rock Maple Street | G13: Hempstead | H13: NY | I13: 11550 | J13: =CONCATENATE(B13," ",C13) -> Robby Sykes
... A1446: 1445 | B1446: Ester | C1446: Acevedo | D1446: NULL | E1446: ester.acevedo@gmail.com | F1446: 671 Miles Court | G1446: San Lorenzo | H1446: CA | I1446: 94580 | J1446: =CONCATENATE(B1446," ",C1446) -> Ester Acevedo

Sheet Store
A1: store_id | B1: store_name | C1: phone | D1: email | E1: street | F1: city | G1: state | H1: zip_code
A2: 1 | B2: Santa Cruz Bikes | C2: (831) 476-4321 | D2: santacruz@bikes.shop | E2: 3700 Portola Drive | F2: Santa Cruz | G2: CA | H2: 95060
A3: 2 | B3: Baldwin Bikes | C3: (516) 379-8888 | D3: baldwin@bikes.shop | E3: 4200 Chestnut Lane | F3: Baldwin | G3: NY | H3: 11432
A4: 3 | B4: Rowlett Bikes | C4: (972) 530-5555 | D4: rowlett@bikes.shop | E4: 8000 Fairway Avenue | F4: Rowlett | G4: TX | H4: 75088

Sheet Staff
A1: staff_id | B1: first_name | C1: last_name | D1: email | E1: phone | F1: active | G1: store_id | H1: manager_id | I1: staff name
A2: 1 | B2: Fabiola | C2: Jackson | D2: fabiola.jackson@bikes.shop | E2: (831) 555-5554 | F2: 1 | G2: 1 | H2: NULL | I2: =CONCATENATE(B2," ",C2) -> Fabiola Jackson
A3: 2 | B3: Mireya | C3: Copeland | D3: mireya.copeland@bikes.shop | E3: (831) 555-5555 | F3: 1 | G3: 1 | H3: 1 | I3: =CONCATENATE(B3," ",C3) -> Mireya Copeland
A4: 3 | B4: Genna | C4: Serrano | D4: genna.serrano@bikes.shop | E4: (831) 555-5556 | F4: 1 | G4: 1 | H4: 2 | I4: =CONCATENATE(B4," ",C4) -> Genna Serrano
A5: 4 | B5: Virgie | C5: Wiggins | D5: virgie.wiggins@bikes.shop | E5: (831) 555-5557 | F5: 1 | G5: 1 | H5: 2 | I5: =CONCATENATE(B5," ",C5) -> Virgie Wiggins
A6: 5 | B6: Jannette | C6: David | D6: jannette.david@bikes.shop | E6: (516) 379-4444 | F6: 1 | G6: 2 | H6: 1 | I6: =CONCATENATE(B6," ",C6) -> Jannette David
A7: 6 | B7: Marcelene | C7: Boyer | D7: marcelene.boyer@bikes.shop | E7: (516) 379-4445 | F7: 1 | G7: 2 | H7: 5 | I7: =CONCATENATE(B7," ",C7) -> Marcelene Boyer
A8: 7 | B8: Venita | C8: Daniel | D8: venita.daniel@bikes.shop | E8: (516) 379-4446 | F8: 1 | G8: 2 | H8: 5 | I8: =CONCATENATE(B8," ",C8) -> Venita Daniel
A9: 8 | B9: Kali | C9: Vargas | D9: kali.vargas@bikes.shop | E9: (972) 530-5555 | F9: 1 | G9: 3 | H9: 1 | I9: =CONCATENATE(B9," ",C9) -> Kali Vargas
A10: 9 | B10: Layla | C10: Terrell | D10: layla.terrell@bikes.shop | E10: (972) 530-5556 | F10: 1 | G10: 3 | H10: 7 | I10: =CONCATENATE(B10," ",C10) -> Layla Terrell
A11: 10 | B11: Bernardine | C11: Houston | D11: bernardine.houston@bikes.shop | E11: (972) 530-5557 | F11: 1 | G11: 3 | H11: 7 | I11: =CONCATENATE(B11," ",C11) -> Bernardine Houston
