Workbook

Sheet Pivot Table
A1: product_id | B1: product name | C1: total_revenue | D1: estimated_cost | E1: profit_margin_percent
A2: 157 | B2: =VLOOKUP(A2,'Product Dataset'!A:B,2,FALSE) -> Trek Domane SL Frameset Women's - 2018 | C2: 6174.9905 | D2: 4549.993 | E2: 26.32
A3: 218 | B3: =VLOOKUP(A3,'Product Dataset'!A:B,2,FALSE) -> Electra Cruiser 7D - 2016/2017/2018 | C3: 303.9905 | D3: 223.993 | E3: 26.32
A4: 289 | B4: =VLOOKUP(A4,'Product Dataset'!A:B,2,FALSE) -> Electra Superbolt 1 20 - 2018 | C4: 607.981 | D4: 447.986 | E4: 26.32 | H4: Sum of total_revenue
A5: 201 | B5: =VLOOKUP(A5,'Product Dataset'!A:B,2,FALSE) -> Trek Powerfly 5 FS - 2018 | C5: 4274.9905 | D5: 3149.993 | E5: 26.32 | H5: 7689116.6
A6: 224 | B6: =VLOOKUP(A6,'Product Dataset'!A:B,2,FALSE) -> Electra Cruiser Lux 7D - 2018 | C6: 1823.962 | D6: 1343.972 | E6: 26.32
A7: 138 | B7: =VLOOKUP(A7,'Product Dataset'!A:B,2,FALSE) -> Trek Fuel EX 5 Plus - 2018 | C7: 12824.943 | D7: 9449.958 | E7: 26.32
A8: 270 | B8: =VLOOKUP(A8,'Product Dataset'!A:B,2,FALSE) -> Trek Precaliber 16 Boy's - 2018 | C8: 199.4905 | D8: 146.993 | E8: 26.32
A9: 315 | B9: =VLOOKUP(A9,'Product Dataset'!A:B,2,FALSE) -> Electra Townie Original 21D Ladies' - 2018 | C9: 1063.981 | D9: 783.986 | E9: 26.32
A10: 243 | B10: =VLOOKUP(A10,'Product Dataset'!A:B,2,FALSE) -> Electra Townie Original 21D EQ Ladies' - 2018 | C10: 3875.943 | D10: 2855.958 | E10: 26.32
A11: 192 | B11: =VLOOKUP(A11,'Product Dataset'!A:B,2,FALSE) -> Electra Townie Go! 8i - 2017/2018 | C11: 2469.9905 | D11: 1819.993 | E11: 26.32
A12: 177 | B12: =VLOOKUP(A12,'Product Dataset'!A:B,2,FALSE) -> Trek Domane SLR 6 Disc - 2018 | C12: 10449.981 | D12: 7699.986 | E12: 26.32
A13: 287 | B13: =VLOOKUP(A13,'Product Dataset'!A:B,2,FALSE) -> Electra Straight 8 1 (16-inch) - Boy's - 2018 | C13: 265.9905 | D13: 195.993 | E13: 26.32
A14: 167 | B14: =VLOOKUP(A14,'Product Dataset'!A:B,2,FALSE) -> Surly ECR Frameset - 2018 | C14: 712.4905 | D14: 524.993 | E14: 26.32
A15: 211 | B15: =VLOOKUP(A15,'Product Dataset'!A:B,2,FALSE) -> Surly Straggler 650b - 2018 | C15: 2943.1 | D15: 2168.6 | E15: 26.32
A16: 290 | B16: =VLOOKUP(A16,'Product Dataset'!A:B,2,FALSE) -> Electra Superbolt 3i 20 - 2018 | C16: 351.4905 | D16: 258.993 | E16: 26.32
A17: 280 | B17: =VLOOKUP(A17,'Product Dataset'!A:B,2,FALSE) -> Trek Superfly 24 - 2017/2018 | C17: 465.4905 | D17: 342.993 | E17: 26.32
... A308: 314 | B308: =VLOOKUP(A308,'Product Dataset'!A:B,2,FALSE) -> Electra Townie Original 21D EQ Ladies' - 2018 | C308: 1087.984 | D308: 951.986 | E308: 12.5

Sheet Product Dataset
A1: product_id | B1: product_name
A2: 2 | B2: Ritchey Timberwolf Frameset - 2016
A3: 3 | B3: Surly Wednesday Frameset - 2016
A4: 4 | B4: Trek Fuel EX 8 29 - 2016
A5: 5 | B5: Heller Shagamaw Frame - 2016
A6: 6 | B6: Surly Ice Cream Truck Frameset - 2016
A7: 7 | B7: Trek Slash 8 27.5 - 2016
A8: 8 | B8: Trek Remedy 29 Carbon Frameset - 2016
A9: 9 | B9: Trek Conduit+ - 2016
A10: 10 | B10: Surly Straggler - 2016
A11: 11 | B11: Surly Straggler 650b - 2016
A12: 12 | B12: Electra Townie Original 21D - 2016
A13: 13 | B13: Electra Cruiser 1 (24-Inch) - 2016
... A308: 315 | B308: Electra Townie Original 21D Ladies' - 2018
